falcon/__init__.py
falcon/__main__.py
falcon/configs.py
falcon/logs.py
falcon/search.py
falcon/utils.py
falcon_datamover-1.0.8.dist-info/LICENSE
falcon_datamover-1.0.8.dist-info/METADATA
falcon_datamover-1.0.8.dist-info/WHEEL
falcon_datamover-1.0.8.dist-info/entry_points.txt
falcon_datamover-1.0.8.dist-info/top_level.txt
falcon_datamover-1.0.8.dist-info/RECORD
