Metadata-Version: 2.1
Name: falcon-datamover
Version: 1.0.8
Summary: Online File Transfer Optimization
Author-email: Md Arifuzzaman <arif@nevada.unr.edu>
License: MIT License
Project-URL: Homepage, https://github.com/arif-zaman/falcon-datamover
Keywords: data-transfer,high-performance-networks
Classifier: License :: OSI Approved :: MIT License
Classifier: Programming Language :: Python :: 3
Requires-Python: >=3.6
License-File: LICENSE
Requires-Dist: joblib >=1.2.0
Requires-Dist: numpy ==1.22.0
Requires-Dist: pyaml ==20.4.0
Requires-Dist: PyYAML >=5.4.1
Requires-Dist: scikit-optimize >=0.8.1
Requires-Dist: scipy >=1.5.4
Requires-Dist: threadpoolctl >=2.1.0
Provides-Extra: dev
Requires-Dist: black ; extra == 'dev'
Requires-Dist: bumpver ; extra == 'dev'
Requires-Dist: isort ; extra == 'dev'
Requires-Dist: pip-tools ; extra == 'dev'
Requires-Dist: pytest ; extra == 'dev'
